stravatools/__init__.py
stravatools/client.py
stravatools/scraper.py
stravatools/_intern/__init__.py
stravatools/_intern/tools.py
stravatools/_intern/units.py
stravatools/cli/__init__.py
stravatools/cli/click_shell_plus.py
stravatools/cli/commands.py
stravatools/cli/shell.py
strava_tools-0.2.0.dist-info/LICENSE
strava_tools-0.2.0.dist-info/METADATA
strava_tools-0.2.0.dist-info/WHEEL
strava_tools-0.2.0.dist-info/entry_points.txt
strava_tools-0.2.0.dist-info/top_level.txt
strava_tools-0.2.0.dist-info/RECORD
