Metadata-Version: 2.1
Name: strava-tools
Version: 0.2.0
Summary: Strava Command-Line Tools
Home-page: https://github.com/terrettaz/strava-tools
Author: Pierrick Terrettaz
Author-email: pierrick@gmail.com
License: MIT
Platform: UNKNOWN
Classifier: License :: OSI Approved :: MIT License
Classifier: Development Status :: 3 - Alpha
Classifier: Natural Language :: English
Classifier: Topic :: Utilities
Requires-Python: >=3.5
Requires-Dist: beautifulsoup4 (>=4)
Requires-Dist: bs4 (>=0.0.1)
Requires-Dist: lxml (>=4)
Requires-Dist: requests (>=2)
Requires-Dist: texttables (>=1.0.0)
Requires-Dist: click (==7.1.2)
Requires-Dist: click-shell (>=2.0)
Requires-Dist: click-spinner (>=0.1.10)
